md2sheet/__init__.py
md2sheet/md2sheet.py
md2sheet-0.2.2.dist-info/LICENSE
md2sheet-0.2.2.dist-info/METADATA
md2sheet-0.2.2.dist-info/WHEEL
md2sheet-0.2.2.dist-info/entry_points.txt
md2sheet-0.2.2.dist-info/RECORD
