Metadata-Version: 2.1
Name: md2sheet
Version: 0.2.2
Summary: A cli tool for convert markdown into sheet(xlsx).
Home-page: https://github.com/cybershang/md2sheet
License: MIT
Keywords: convert,structured,markdown,spreadsheet,csv,markdown_2_json,typer
Author: Yingjie Shang
Author-email: dev@yingjie.space
Requires-Python: >=3.8,<4.0
Classifier: Development Status :: 3 - Alpha
Classifier: Environment :: Console
Classifier: License :: OSI Approved :: MIT License
Classifier: Operating System :: OS Independent
Classifier: Programming Language :: Python :: 3
Classifier: Programming Language :: Python :: 3.8
Classifier: Programming Language :: Python :: 3.9
Classifier: Programming Language :: Python :: 3.10
Classifier: Programming Language :: Python :: 3.11
Classifier: Programming Language :: Python :: 3.12
Classifier: Topic :: File Formats
Classifier: Topic :: Office/Business :: Financial :: Spreadsheet
Classifier: Topic :: Text Processing :: Markup :: Markdown
Classifier: Topic :: Utilities
Requires-Dist: markdown-to-json (>=2.1.0,<3.0.0)
Requires-Dist: openpyxl (>=3.1.2,<4.0.0)
Requires-Dist: pylint (>=3.0.2,<4.0.0)
Requires-Dist: typer[all] (>=0.9.0,<0.10.0)
Project-URL: Repository, https://github.com/cybershang/md2sheet
